[
    {
        "text": "self driving",
        "size": "4931"
    },
    {
        "text": "driving cars",
        "size": "4011"
    },
    {
        "text": "self cars",
        "size": "4002"
    },
    {
        "text": "driving car",
        "size": "544"
    },
    {
        "text": "self car",
        "size": "538"
    },
    {
        "text": "uber self",
        "size": "432"
    },
    {
        "text": "self via",
        "size": "430"
    },
    {
        "text": "driving via",
        "size": "428"
    },
    {
        "text": "uber driving",
        "size": "426"
    },
    {
        "text": "uber cars",
        "size": "374"
    }
]