[
    {
        "text": "artificial",
        "size": "3647"
    },
    {
        "text": "intelligence",
        "size": "3573"
    },
    {
        "text": "amp",
        "size": "420"
    },
    {
        "text": "learning",
        "size": "397"
    },
    {
        "text": "machine",
        "size": "385"
    },
    {
        "text": "google",
        "size": "355"
    },
    {
        "text": "future",
        "size": "350"
    },
    {
        "text": "via",
        "size": "340"
    },
    {
        "text": "data",
        "size": "290"
    },
    {
        "text": "use",
        "size": "288"
    },
    {
        "text": "technology",
        "size": "260"
    },
    {
        "text": "research",
        "size": "257"
    },
    {
        "text": "could",
        "size": "243"
    },
    {
        "text": "university",
        "size": "203"
    },
    {
        "text": "robot",
        "size": "195"
    },
    {
        "text": "musk",
        "size": "191"
    },
    {
        "text": "human",
        "size": "187"
    },
    {
        "text": "news",
        "size": "185"
    },
    {
        "text": "business",
        "size": "183"
    },
    {
        "text": "microsoft",
        "size": "181"
    },
    {
        "text": "great",
        "size": "175"
    },
    {
        "text": "boycott",
        "size": "173"
    },
    {
        "text": "tech",
        "size": "165"
    },
    {
        "text": "killer",
        "size": "163"
    },
    {
        "text": "search",
        "size": "160"
    },
    {
        "text": "life",
        "size": "158"
    },
    {
        "text": "dictator",
        "size": "155"
    },
    {
        "text": "create",
        "size": "154"
    },
    {
        "text": "immortal",
        "size": "153"
    },
    {
        "text": "experts",
        "size": "152"
    },
    {
        "text": "know",
        "size": "150"
    },
    {
        "text": "apple",
        "size": "149"
    },
    {
        "text": "work",
        "size": "146"
    },
    {
        "text": "ibm",
        "size": "145"
    },
    {
        "text": "using",
        "size": "144"
    },
    {
        "text": "one",
        "size": "138"
    },
    {
        "text": "help",
        "size": "131"
    },
    {
        "text": "best",
        "size": "128"
    },
    {
        "text": "powered",
        "size": "128"
    },
    {
        "text": "make",
        "size": "127"
    },
    {
        "text": "program",
        "size": "126"
    },
    {
        "text": "uwaterloo",
        "size": "120"
    },
    {
        "text": "elon",
        "size": "119"
    },
    {
        "text": "uses",
        "size": "118"
    },
    {
        "text": "banking",
        "size": "115"
    },
    {
        "text": "coming",
        "size": "115"
    },
    {
        "text": "get",
        "size": "112"
    },
    {
        "text": "cow",
        "size": "109"
    },
    {
        "text": "fitbits",
        "size": "108"
    },
    {
        "text": "fintech",
        "size": "106"
    }
]